ChaolingQihaoVol2/Dockerfile
ChaolingQihaoVol2/README.md
ChaolingQihaoVol2/__init__.py
ChaolingQihaoVol2/__main__.py
ChaolingQihaoVol2/file.epub
ChaolingQihaoVol2/index.html
ChaolingQihaoVol2/css/__init__.py
ChaolingQihaoVol2/css/annotations.css
ChaolingQihaoVol2/css/main.css
ChaolingQihaoVol2/css/normalize.css
ChaolingQihaoVol2/css/popup.css
ChaolingQihaoVol2/font/__init__.py
ChaolingQihaoVol2/font/fontello.eot
ChaolingQihaoVol2/font/fontello.svg
ChaolingQihaoVol2/font/fontello.ttf
ChaolingQihaoVol2/font/fontello.woff
ChaolingQihaoVol2/img/__init__.py
ChaolingQihaoVol2/img/annotator-glyph-sprite.png
ChaolingQihaoVol2/img/annotator-icon-sprite.png
ChaolingQihaoVol2/img/apple-touch-icon.png
ChaolingQihaoVol2/img/cancelfullscreen.png
ChaolingQihaoVol2/img/close.png
ChaolingQihaoVol2/img/fullscreen.png
ChaolingQihaoVol2/img/loader.gif
ChaolingQihaoVol2/img/menu-icon.png
ChaolingQihaoVol2/img/save.png
ChaolingQihaoVol2/img/saved.png
ChaolingQihaoVol2/img/settings-s.png
ChaolingQihaoVol2/img/settings.png
ChaolingQihaoVol2/img/star.png
ChaolingQihaoVol2/js/__init__.py
ChaolingQihaoVol2/js/epub.js
ChaolingQihaoVol2/js/epub.min.js
ChaolingQihaoVol2/js/epub.min.map
ChaolingQihaoVol2/js/hooks.min.js
ChaolingQihaoVol2/js/hooks.min.map
ChaolingQihaoVol2/js/reader.js
ChaolingQihaoVol2/js/reader.js.map
ChaolingQihaoVol2/js/reader.min.js
ChaolingQihaoVol2/js/reader.min.map
ChaolingQihaoVol2/js/hooks/__init__.py
ChaolingQihaoVol2/js/hooks/extensions/__init__.py
ChaolingQihaoVol2/js/hooks/extensions/highlight.js
ChaolingQihaoVol2/js/libs/__init__.py
ChaolingQihaoVol2/js/libs/jquery.min.js
ChaolingQihaoVol2/js/libs/localforage.min.js
ChaolingQihaoVol2/js/libs/screenfull.js
ChaolingQihaoVol2/js/libs/screenfull.min.js
ChaolingQihaoVol2/js/libs/zip.min.js
ChaolingQihaoVol2/js/plugins/__init__.py
ChaolingQihaoVol2/js/plugins/hypothesis.js
ChaolingQihaoVol2/js/plugins/search.js
chaoling_qihao_vol2-2022.10.9.1.dist-info/METADATA
chaoling_qihao_vol2-2022.10.9.1.dist-info/WHEEL
chaoling_qihao_vol2-2022.10.9.1.dist-info/entry_points.txt
chaoling_qihao_vol2-2022.10.9.1.dist-info/top_level.txt
chaoling_qihao_vol2-2022.10.9.1.dist-info/RECORD
